[{"id":"user-image-asadadetijuana.jpeg","publicUrl":"np://user.desktop.nicepage.com/Site_1550202704/images/asadadetijuana.jpeg","size":36249,"hash":"lz/C/4yuakJFE3UqEHRui6PbGbg=","fileName":"asadadetijuana.jpeg","name":"asadadetijuana","width":474,"height":355,"thumbnail":{"url":"np://user.desktop.nicepage.com/Site_1550202704/images/thumbnails/asadadetijuana.jpeg","width":250,"height":187},"folderId":null,"usages":["122998333"]},{"id":"user-image-camaronceviche.jpeg","publicUrl":"np://user.desktop.nicepage.com/Site_1550202704/images/camaronceviche.jpeg","size":22866,"hash":"EmZyUGydXSZAgqcmLNeCY9ty88c=","fileName":"camaronceviche.jpeg","name":"camaronceviche","width":279,"height":186,"thumbnail":{"url":"np://user.desktop.nicepage.com/Site_1550202704/images/thumbnails/camaronceviche.jpeg","width":250,"height":167},"folderId":null,"usages":["122998333"]},{"id":"user-image-tacoestilobajo.jpeg","publicUrl":"np://user.desktop.nicepage.com/Site_1550202704/images/tacoestilobajo.jpeg","size":11596,"hash":"q86PAnQAi9fKVVN9ReITkRlPef0=","fileName":"tacoestilobajo.jpeg","name":"tacoestilobajo","width":175,"height":190,"thumbnail":{"url":"np://user.desktop.nicepage.com/Site_1550202704/images/thumbnails/tacoestilobajo.jpeg","height":190,"width":175,"length":11596,"type":"jpg"},"folderId":null,"usages":["122998333"]},{"id":"user-image-cesartipotijuana.jpeg","publicUrl":"np://user.desktop.nicepage.com/Site_1550202704/images/cesartipotijuana.jpeg","size":16331,"hash":"Lfh8zAj2M7CDsW05GN98b9iQ0Xg=","fileName":"cesartipotijuana.jpeg","name":"cesartipotijuana","width":313,"height":180,"thumbnail":{"url":"np://user.desktop.nicepage.com/Site_1550202704/images/thumbnails/cesartipotijuana.jpeg","width":250,"height":144},"folderId":null,"usages":["122998333"]},{"id":"user-image-TIJUANAAUA.jpeg","publicUrl":"np://user.desktop.nicepage.com/Site_1550202704/images/TIJUANAAUA.jpeg","size":18483,"hash":"aVazXXZLdDNkoiYyk3gGwU2GGw0=","fileName":"TIJUANAAUA.jpeg","name":"TIJUANAAUA","width":288,"height":181,"thumbnail":{"url":"np://user.desktop.nicepage.com/Site_1550202704/images/thumbnails/TIJUANAAUA.jpeg","width":250,"height":157},"folderId":null,"usages":["122998333"]},{"id":"user-image-tijuana.jpeg","publicUrl":"np://user.desktop.nicepage.com/Site_1550202704/images/tijuana.jpeg","size":31329,"hash":"Aq4w3bR1sd9Vy3TEK46QJPynrsM=","fileName":"tijuana.jpeg","name":"tijuana","width":474,"height":300,"thumbnail":{"url":"np://user.desktop.nicepage.com/Site_1550202704/images/thumbnails/tijuana.jpeg","width":250,"height":158},"folderId":null,"usages":[]},{"id":"user-image-5464e56.jpg","publicUrl":"np://user.desktop.nicepage.com/Site_1550202704/images/5464e56.jpg","size":106930,"hash":"P9Zc22sr4RRRbebI7OLGIzVyqaE=","fileName":"5464e56.jpg","name":"5464e56","width":710,"height":710,"thumbnail":{"url":"np://user.desktop.nicepage.com/Site_1550202704/images/thumbnails/5464e56.jpg","width":250,"height":250},"folderId":null,"originalUrl":"https://assets.nicepagecdn.com/d2cc3eaa/1292318/images/5464e56.jpg","usages":[]},{"id":"user-image-Untitled-2.jpg","publicUrl":"np://user.desktop.nicepage.com/Site_1550202704/images/Untitled-2.jpg","size":79570,"hash":"Wt/ETaE6vRtnZ3p/1RXjDqd1ehQ=","fileName":"Untitled-2.jpg","name":"Untitled-2","width":710,"height":710,"thumbnail":{"url":"np://user.desktop.nicepage.com/Site_1550202704/images/thumbnails/Untitled-2.jpg","width":250,"height":250},"folderId":null,"originalUrl":"https://assets.nicepagecdn.com/d2cc3eaa/1292318/images/Untitled-2.jpg","usages":[]},{"id":"user-image-sfrt-min.jpg","publicUrl":"np://user.desktop.nicepage.com/Site_1550202704/images/sfrt-min.jpg","size":111277,"hash":"AZ1tkswnRJbIHbvzwLyTFCDSkqU=","fileName":"sfrt-min.jpg","name":"sfrt-min","width":1000,"height":1017,"thumbnail":{"url":"np://user.desktop.nicepage.com/Site_1550202704/images/thumbnails/sfrt-min.jpg","width":246,"height":250},"folderId":null,"originalUrl":"//images03.nicepagecdn.com/c461c07a441a5d220e8feb1a/fcbc197199b75e9a86374f3c/sfrt-min.jpg","usages":[]},{"id":"user-image-45345.jpg","publicUrl":"np://user.desktop.nicepage.com/Site_1550202704/images/45345.jpg","size":162615,"hash":"boiODfYoRp1NDvCSA1OHPfxKs4M=","fileName":"45345.jpg","name":"45345","width":1380,"height":920,"thumbnail":{"url":"np://user.desktop.nicepage.com/Site_1550202704/images/thumbnails/45345.jpg","width":250,"height":167},"folderId":null,"originalUrl":"https://assets.nicepagecdn.com/d2cc3eaa/1292318/images/45345.jpg","usages":[]},{"id":"user-image-46456.jpg","publicUrl":"np://user.desktop.nicepage.com/Site_1550202704/images/46456.jpg","size":163239,"hash":"SJfFh7mg9ml7FZU0JJOMFOPnf0g=","fileName":"46456.jpg","name":"46456","width":740,"height":1110,"thumbnail":{"url":"np://user.desktop.nicepage.com/Site_1550202704/images/thumbnails/46456.jpg","width":167,"height":250},"folderId":null,"originalUrl":"https://assets.nicepagecdn.com/d2cc3eaa/1292318/images/46456.jpg","usages":[]},{"id":"user-image-uyu.jpg","publicUrl":"np://user.desktop.nicepage.com/Site_1550202704/images/uyu.jpg","size":168654,"hash":"ZpG+WxZSNPBxEjzhP7BcoamyDTU=","fileName":"uyu.jpg","name":"uyu","width":740,"height":1110,"thumbnail":{"url":"np://user.desktop.nicepage.com/Site_1550202704/images/thumbnails/uyu.jpg","width":167,"height":250},"folderId":null,"originalUrl":"https://assets.nicepagecdn.com/d2cc3eaa/1292318/images/uyu.jpg","usages":[]},{"id":"user-image-56645.jpg","publicUrl":"np://user.desktop.nicepage.com/Site_1550202704/images/56645.jpg","size":506045,"hash":"TKyCSqMwUu5fe+41fUw4rmJz5OY=","fileName":"56645.jpg","name":"56645","width":1980,"height":1321,"thumbnail":{"url":"np://user.desktop.nicepage.com/Site_1550202704/images/thumbnails/56645.jpg","width":250,"height":167},"folderId":null,"originalUrl":"https://assets.nicepagecdn.com/d2cc3eaa/1292318/images/56645.jpg","usages":[]},{"id":"user-image-56767.jpg","publicUrl":"np://user.desktop.nicepage.com/Site_1550202704/images/56767.jpg","size":123075,"hash":"InwSFDC/yl0vnnWEOV+ZQlUCTXc=","fileName":"56767.jpg","name":"56767","width":740,"height":1022,"thumbnail":{"url":"np://user.desktop.nicepage.com/Site_1550202704/images/thumbnails/56767.jpg","width":181,"height":250},"folderId":null,"originalUrl":"https://assets.nicepagecdn.com/d2cc3eaa/1292318/images/56767.jpg","usages":[]},{"id":"user-image-erstg.jpg","publicUrl":"np://user.desktop.nicepage.com/Site_1550202704/images/erstg.jpg","size":182258,"hash":"KVsl013w840NG8/gDA2TwnEXMZM=","fileName":"erstg.jpg","name":"erstg","width":900,"height":900,"thumbnail":{"url":"np://user.desktop.nicepage.com/Site_1550202704/images/thumbnails/erstg.jpg","width":250,"height":250},"folderId":null,"originalUrl":"//images03.nicepagecdn.com/c461c07a441a5d220e8feb1a/6a8c93a784ac5709b4bfb6a0/erstg.jpg","usages":[]},{"id":"user-image-tyty.jpg","publicUrl":"np://user.desktop.nicepage.com/Site_1550202704/images/tyty.jpg","size":118518,"hash":"gpGJKis9N8PntXLDL6jUxHmcb/s=","fileName":"tyty.jpg","name":"tyty","width":710,"height":710,"thumbnail":{"url":"np://user.desktop.nicepage.com/Site_1550202704/images/thumbnails/tyty.jpg","width":250,"height":250},"folderId":null,"originalUrl":"https://assets.nicepagecdn.com/d2cc3eaa/1292318/images/tyty.jpg","usages":[]},{"id":"user-image-547y54r.jpg","publicUrl":"np://user.desktop.nicepage.com/Site_1550202704/images/547y54r.jpg","size":100475,"hash":"frHQAMGUj2BeJEFfDs+TqSxS+hA=","fileName":"547y54r.jpg","name":"547y54r","width":710,"height":710,"thumbnail":{"url":"np://user.desktop.nicepage.com/Site_1550202704/images/thumbnails/547y54r.jpg","width":250,"height":250},"folderId":null,"originalUrl":"https://assets.nicepagecdn.com/d2cc3eaa/1292318/images/547y54r.jpg","usages":[]},{"id":"user-image-545345.jpg","publicUrl":"np://user.desktop.nicepage.com/Site_1550202704/images/545345.jpg","size":116794,"hash":"MO5qYzdfWgEe+wPkxpivWTsjKPM=","fileName":"545345.jpg","name":"545345","width":710,"height":710,"thumbnail":{"url":"np://user.desktop.nicepage.com/Site_1550202704/images/thumbnails/545345.jpg","width":250,"height":250},"folderId":null,"originalUrl":"https://assets.nicepagecdn.com/d2cc3eaa/1292318/images/545345.jpg","usages":[]},{"id":"user-image-6547.jpg","publicUrl":"np://user.desktop.nicepage.com/Site_1550202704/images/6547.jpg","size":133311,"hash":"9zGZFfhiXwR6szvagg2aZJGAujU=","fileName":"6547.jpg","name":"6547","width":710,"height":710,"thumbnail":{"url":"np://user.desktop.nicepage.com/Site_1550202704/images/thumbnails/6547.jpg","width":250,"height":250},"folderId":null,"originalUrl":"https://assets.nicepagecdn.com/d2cc3eaa/1292318/images/6547.jpg","usages":[]},{"id":"user-image-tyr.jpg","publicUrl":"np://user.desktop.nicepage.com/Site_1550202704/images/tyr.jpg","size":171053,"hash":"BB1D2zcKDW1FI9ggNmwwr7boVzQ=","fileName":"tyr.jpg","name":"tyr","width":920,"height":920,"thumbnail":{"url":"np://user.desktop.nicepage.com/Site_1550202704/images/thumbnails/tyr.jpg","width":250,"height":250},"folderId":null,"originalUrl":"https://assets.nicepagecdn.com/d2cc3eaa/1292318/images/tyr.jpg","usages":[]},{"id":"user-image-56677.jpg","publicUrl":"np://user.desktop.nicepage.com/Site_1550202704/images/56677.jpg","size":182501,"hash":"+fR3MW9Z62MuDD9VEXs66IUmJXU=","fileName":"56677.jpg","name":"56677","width":740,"height":1110,"thumbnail":{"url":"np://user.desktop.nicepage.com/Site_1550202704/images/thumbnails/56677.jpg","width":167,"height":250},"folderId":null,"originalUrl":"https://assets.nicepagecdn.com/d2cc3eaa/1292318/images/56677.jpg","usages":[]}]
